long_task_printer/__init__.py
long_task_printer/error.py
long_task_printer/formatting.py
long_task_printer/limited_sequence.py
long_task_printer/unlimited_sequence.py
long_task_printer-0.1.2.dist-info/LICENSE
long_task_printer-0.1.2.dist-info/METADATA
long_task_printer-0.1.2.dist-info/WHEEL
long_task_printer-0.1.2.dist-info/RECORD
