Metadata-Version: 2.1
Name: long_task_printer
Version: 0.1.2
Summary: Measure iterations in a long-running task, provide a time estimation
Author: Andrew Radev
Author-email: andrey.radev@gmail.com
Requires-Python: >=3.8,<4.0
Classifier: Programming Language :: Python :: 3
Classifier: Programming Language :: Python :: 3.8
Classifier: Programming Language :: Python :: 3.9
Classifier: Programming Language :: Python :: 3.10
Classifier: Programming Language :: Python :: 3.11
Classifier: Programming Language :: Python :: 3.12
